{
  "title": "William Collingbourne",
  "content-preview": "William Collingborn (c. 1435\u20131484) was an English landowner and administrator. He was an opponent of King Richard III \u2013 corresponding with his enemies and penning a famous lampoon \u2013 and was eventually executed for treason.\n\n\n== Family background and marriage ==\nCollingbourne's family originated from",
  "url": "https://en.wikipedia.org/wiki/William_Collingbourne",
  "pageid": 23020170,
  "title-terms": {
    "william": 1,
    "collingbourne": 1
  },
  "content-terms": {
    "william": 7,
    "collingborn": 1,
    "c": 1,
    "1435\u20131484": 1,
    "english": 1,
    "landowner": 1,
    "administrator": 2,
    "opponent": 2,
    "king": 11,
    "richard": 10,
    "iii": 3,
    "\u2013": 8,
    "corresponding": 1,
    "enemies": 1,
    "penning": 1,
    "famous": 1,
    "lampoon": 5,
    "eventually": 2,
    "executed": 3,
    "treason": 3,
    "family": 2,
    "background": 1,
    "marriage": 3,
    "collingbournes": 6,
    "originated": 1,
    "villages": 1,
    "bearing": 1,
    "name": 2,
    "collingbourn": 1,
    "abbas": 1,
    "collingbourne": 17,
    "ducis": 1,
    "wiltshire": 11,
    "first": 4,
    "known": 1,
    "ancestor": 1,
    "thomas": 4,
    "colynborn": 1,
    "marleberg": 1,
    "marlborough": 3,
    "lived": 1,
    "1377": 1,
    "grandson": 1,
    "bedewynde": 1,
    "great": 1,
    "bedwyn": 1,
    "clerk": 1,
    "peace": 4,
    "1390": 1,
    "member": 1,
    "parliament": 1,
    "1402": 1,
    "collector": 1,
    "taxes": 1,
    "1413": 1,
    "1417": 1,
    "married": 4,
    "jean": 1,
    "russel": 1,
    "three": 3,
    "sons": 1,
    "called": 1,
    "robert": 3,
    "john": 5,
    "attended": 1,
    "college": 1,
    "1422\u20131427": 1,
    "received": 1,
    "several": 2,
    "offices": 2,
    "1441": 1,
    "1462": 1,
    "however": 1,
    "probably": 2,
    "historical": 1,
    "fame": 1,
    "rather": 1,
    "uncle": 1,
    "namesake": 1,
    "mentioned": 2,
    "son": 1,
    "sometime": 1,
    "1474": 2,
    "margaret": 3,
    "daughter": 1,
    "heiress": 1,
    "norwood": 1,
    "widow": 1,
    "sir": 1,
    "james": 4,
    "pykeryng": 1,
    "least": 1,
    "two": 3,
    "children": 1,
    "edward": 3,
    "elen": 1,
    "second": 1,
    "produced": 1,
    "daughters": 1,
    "later": 3,
    "george": 1,
    "chaderton": 1,
    "jane": 1,
    "louder": 1,
    "lowther": 1,
    "mp": 1,
    "1491\u201392": 1,
    "land": 6,
    "owner": 1,
    "according": 1,
    "sources": 1,
    "amassed": 1,
    "northeast": 1,
    "also": 3,
    "acquired": 2,
    "property": 2,
    "city": 1,
    "london": 1,
    "1470s": 1,
    "commissioner": 3,
    "enquiry": 1,
    "farms": 1,
    "grants": 1,
    "money": 1,
    "involved": 2,
    "actions": 1,
    "trespasses": 1,
    "debts": 1,
    "mostly": 1,
    "defendants": 1,
    "kent": 1,
    "suggests": 2,
    "county": 1,
    "well": 2,
    "held": 2,
    "administrative": 1,
    "posts": 1,
    "served": 2,
    "sheriff": 1,
    "1481": 2,
    "1475": 2,
    "1478\u20131481": 1,
    "named": 2,
    "one": 1,
    "would": 4,
    "enquire": 1,
    "certain": 2,
    "treasons": 1,
    "lolardries": 1,
    "heresies": 1,
    "errors": 1,
    "dorset": 3,
    "list": 1,
    "included": 3,
    "edwards": 1,
    "brothers": 1,
    "dukes": 2,
    "clarence": 2,
    "gloucester": 2,
    "execution": 2,
    "1478": 2,
    "among": 4,
    "enquiring": 1,
    "possession": 1,
    "counties": 1,
    "southampton": 1,
    "1482": 1,
    "charge": 2,
    "manors": 1,
    "death": 2,
    "iv": 1,
    "april": 2,
    "1483": 7,
    "appointed": 1,
    "commission": 2,
    "assess": 1,
    "subsidies": 1,
    "granted": 1,
    "late": 1,
    "commons": 1,
    "realm": 1,
    "july": 6,
    "june": 2,
    "duke": 2,
    "came": 1,
    "throne": 1,
    "soon": 1,
    "afterwards": 1,
    "positioned": 1,
    "opposition": 1,
    "new": 3,
    "october": 3,
    "buckinghams": 3,
    "revolt": 2,
    "favour": 1,
    "henry": 7,
    "tudor": 9,
    "walter": 1,
    "hungerford": 1,
    "cheyne": 1,
    "commissions": 2,
    "leaders": 1,
    "around": 1,
    "10": 1,
    "either": 2,
    "1484": 6,
    "asked": 2,
    "yate": 1,
    "contact": 1,
    "marquess": 2,
    "opponents": 1,
    "declare": 1,
    "unto": 1,
    "return": 1,
    "england": 1,
    "power": 1,
    "might": 1,
    "get": 1,
    "feast": 1,
    "st": 2,
    "luke": 1,
    "evangelist": 1,
    "18": 1,
    "next": 1,
    "ensuring": 1,
    "furthermore": 3,
    "advise": 1,
    "french": 2,
    "negotiations": 2,
    "useless": 1,
    "meant": 1,
    "make": 3,
    "war": 1,
    "france": 1,
    "year": 1,
    "correspondence": 5,
    "matter": 1,
    "controversy": 1,
    "gairdner": 2,
    "placed": 1,
    "context": 2,
    "rebellion": 2,
    "indeed": 1,
    "tried": 1,
    "hence": 1,
    "dated": 2,
    "argued": 2,
    "things": 1,
    "located": 1,
    "brittany": 2,
    "left": 1,
    "henrys": 1,
    "attempt": 1,
    "poole": 3,
    "november": 2,
    "corresponds": 1,
    "message": 1,
    "interpretation": 2,
    "put": 2,
    "letter": 2,
    "immediate": 1,
    "aftermath": 1,
    "richards": 3,
    "coronation": 1,
    "6": 1,
    "set": 1,
    "royal": 1,
    "progress": 1,
    "gairdners": 2,
    "words": 1,
    "almost": 1,
    "man": 1,
    "move": 1,
    "usurper": 1,
    "accordingly": 1,
    "contradicted": 1,
    "historians": 1,
    "notably": 1,
    "paul": 1,
    "murray": 1,
    "kendall": 2,
    "treasonous": 1,
    "thus": 1,
    "dorsets": 1,
    "joining": 1,
    "ambassadors": 1,
    "occurred": 1,
    "whereas": 1,
    "mentioning": 1,
    "conclusive": 1,
    "evidence": 1,
    "indicted": 1,
    "writing": 1,
    "various": 1,
    "bills": 1,
    "writings": 1,
    "rhyme": 3,
    "without": 1,
    "specifying": 1,
    "rhymes": 1,
    "fabyans": 1,
    "chronicle": 1,
    "published": 1,
    "1516": 1,
    "relate": 1,
    "pinned": 1,
    "following": 1,
    "door": 1,
    "pauls": 1,
    "cathedral": 1,
    "catte": 1,
    "ratte": 1,
    "lovell": 5,
    "dogge": 1,
    "rulyth": 1,
    "englande": 1,
    "hogge": 1,
    "attacked": 1,
    "principal": 1,
    "aides": 1,
    "referring": 1,
    "names": 2,
    "heraldic": 1,
    "emblems": 1,
    "hog": 1,
    "course": 1,
    "referred": 1,
    "whose": 1,
    "badge": 2,
    "white": 2,
    "boar": 1,
    "dog": 1,
    "francis": 2,
    "viscount": 2,
    "closest": 2,
    "associate": 2,
    "silver": 1,
    "wolf": 1,
    "emblem": 1,
    "cat": 2,
    "rat": 1,
    "made": 1,
    "fun": 1,
    "catesby": 1,
    "ratcliffe": 1,
    "twoliner": 1,
    "embellished": 1,
    "amended": 1,
    "explanation": 1,
    "supposedly": 1,
    "author": 2,
    "mirror": 1,
    "magistrates": 1,
    "reasons": 1,
    "enmity": 1,
    "entirely": 1,
    "clear": 1,
    "1892": 1,
    "h": 1,
    "ramsay": 1,
    "suggested": 1,
    "written": 2,
    "revenge": 1,
    "loss": 2,
    "appear": 1,
    "december": 2,
    "3": 1,
    "mother": 1,
    "cecily": 1,
    "neville": 1,
    "duchess": 2,
    "york": 1,
    "lord": 4,
    "chamberlain": 2,
    "officer": 1,
    "colyngbourne": 1,
    "steward": 1,
    "lands": 1,
    "response": 1,
    "lost": 1,
    "position": 1,
    "may": 1,
    "linked": 1,
    "involvement": 1,
    "dismissed": 1,
    "went": 1,
    "hiding": 1,
    "post": 1,
    "filled": 1,
    "explain": 1,
    "ire": 1,
    "trial": 2,
    "arrested": 1,
    "together": 1,
    "shipowner": 1,
    "turburvyle": 2,
    "charged": 1,
    "oyer": 1,
    "terminer": 1,
    "suffolk": 1,
    "norfolk": 1,
    "earls": 1,
    "surrey": 1,
    "nottingham": 1,
    "viscounts": 1,
    "lisle": 1,
    "barons": 1,
    "including": 2,
    "high": 2,
    "constable": 1,
    "stanley": 1,
    "five": 1,
    "justices": 1,
    "kings": 1,
    "bench": 1,
    "chief": 1,
    "justice": 1,
    "hussey": 1,
    "early": 1,
    "guildhall": 1,
    "convicted": 1,
    "sentenced": 2,
    "prison": 1,
    "apparently": 1,
    "lesser": 1,
    "subsequently": 1,
    "tower": 1,
    "hill": 1,
    "hanging": 1,
    "drawing": 1,
    "quartering": 1,
    "story": 1,
    "historian": 2,
    "stow": 1,
    "recounts": 1,
    "end": 1,
    "hanged": 1,
    "cut": 1,
    "immediately": 1,
    "entrails": 1,
    "extracted": 1,
    "thrown": 1,
    "fire": 1,
    "speedily": 1,
    "done": 1,
    "executioners": 1,
    "pulled": 1,
    "heart": 1,
    "spoke": 1,
    "said": 1,
    "oh": 1,
    "jesus": 1,
    "yet": 1,
    "trouble": 1,
    "hall": 2,
    "relates": 1,
    "merely": 1,
    "making": 1,
    "small": 1,
    "claim": 1,
    "taken": 1,
    "authors": 1,
    "charles": 1,
    "ross": 1,
    "pointed": 1,
    "carefully": 1,
    "suppresses": 1,
    "fact": 1,
    "real": 1,
    "indictment": 1,
    "encouraging": 1,
    "notes": 1
  },
  "title-length": 2,
  "content-length": 729,
  "curious_frequency": 0,
  "uplifting_frequency": 1,
  "entertaining_frequency": 1,
  "sad_frequency": 5,
  "general_frequency": 0
}