{
  "title": "Joseph Dodson",
  "content-preview": "Joseph Reid Dodson JP (1811/12 \u2013 12 October 1890), was the first Mayor of Nelson in New Zealand from 1874. He was a prominent brewer and Resident Magistrate in Nelson and his sixth generation descendants still operate a brewery in the city.\n\n\n== Early life ==\nDodson was originally from England. He a",
  "url": "https://en.wikipedia.org/wiki/Joseph_Dodson",
  "pageid": 29806835,
  "title-terms": {
    "joseph": 1,
    "dodson": 1
  },
  "content-terms": {
    "joseph": 3,
    "reid": 1,
    "dodson": 13,
    "jp": 1,
    "181112": 1,
    "\u2013": 1,
    "12": 3,
    "october": 3,
    "1890": 2,
    "first": 4,
    "mayor": 9,
    "nelson": 7,
    "new": 3,
    "zealand": 1,
    "1874": 6,
    "prominent": 1,
    "brewer": 1,
    "resident": 1,
    "magistrate": 1,
    "sixth": 1,
    "generation": 1,
    "descendants": 2,
    "still": 1,
    "operate": 2,
    "brewery": 11,
    "city": 4,
    "early": 1,
    "life": 1,
    "originally": 1,
    "england": 2,
    "arrived": 1,
    "16": 3,
    "may": 2,
    "1854": 2,
    "melbourne": 3,
    "australia": 1,
    "brig": 1,
    "return": 2,
    "via": 1,
    "wellington": 1,
    "within": 1,
    "days": 1,
    "bought": 2,
    "share": 1,
    "soon": 1,
    "afterwards": 1,
    "returned": 2,
    "sort": 1,
    "business": 3,
    "affairs": 1,
    "wife": 1,
    "four": 1,
    "children": 1,
    "marchioness": 1,
    "arriving": 1,
    "27": 1,
    "september": 2,
    "professional": 1,
    "career": 2,
    "arrival": 1,
    "shares": 2,
    "late": 1,
    "dr": 1,
    "renwick": 1,
    "hooper": 3,
    "co": 2,
    "1855": 1,
    "established": 4,
    "raglan": 1,
    "leased": 1,
    "charles": 1,
    "harleys": 1,
    "bridge": 1,
    "street": 1,
    "1860": 1,
    "sold": 1,
    "went": 2,
    "back": 1,
    "family": 1,
    "six": 1,
    "years": 3,
    "brought": 1,
    "farming": 1,
    "equipment": 1,
    "reseller": 1,
    "goods": 1,
    "took": 2,
    "shareholding": 2,
    "1884": 1,
    "suffered": 1,
    "significant": 1,
    "loss": 1,
    "death": 2,
    "partner": 1,
    "30": 1,
    "george": 1,
    "hoopers": 1,
    "name": 1,
    "changed": 1,
    "j": 1,
    "r": 1,
    "son": 3,
    "henry": 3,
    "joined": 2,
    "1879": 1,
    "duncan": 4,
    "1888": 1,
    "dodsons": 1,
    "daughter": 1,
    "maryann": 1,
    "continued": 1,
    "brewing": 1,
    "greatgrandchildren": 1,
    "matt": 1,
    "callum": 1,
    "boutique": 1,
    "international": 2,
    "acclaim": 1,
    "founders": 1,
    "1999": 1,
    "fully": 1,
    "certified": 1,
    "organic": 1,
    "southern": 1,
    "hemisphere": 1,
    "twice": 1,
    "award": 1,
    "champion": 1,
    "small": 1,
    "australian": 1,
    "beer": 1,
    "awards": 1,
    "political": 1,
    "former": 1,
    "member": 1,
    "board": 1,
    "works": 2,
    "elected": 5,
    "councillor": 1,
    "possibly": 1,
    "fellow": 1,
    "councillors": 3,
    "council": 6,
    "meeting": 4,
    "1": 1,
    "appointed": 1,
    "justice": 1,
    "peace": 1,
    "receive": 1,
    "salary": 1,
    "although": 1,
    "entertained": 1,
    "visiting": 1,
    "dignitaries": 1,
    "expense": 1,
    "governor": 2,
    "sir": 1,
    "james": 1,
    "fergusson": 1,
    "behalf": 1,
    "provoked": 1,
    "debate": 1,
    "local": 2,
    "papers": 1,
    "behaviour": 1,
    "provincial": 3,
    "superintendent": 1,
    "comparison": 1,
    "term": 4,
    "negotiations": 1,
    "began": 1,
    "gas": 2,
    "government": 3,
    "owned": 1,
    "facility": 1,
    "lighting": 1,
    "sought": 1,
    "employ": 1,
    "town": 1,
    "clerk": 1,
    "rate": 1,
    "collector": 1,
    "december": 2,
    "reconfirmed": 1,
    "1875": 3,
    "conflict": 1,
    "finances": 1,
    "bankrupt": 1,
    "resigned": 1,
    "8": 1,
    "january": 2,
    "special": 1,
    "remaining": 1,
    "held": 2,
    "appoint": 1,
    "one": 1,
    "forthcoming": 1,
    "public": 1,
    "friday": 1,
    "determine": 1,
    "wishes": 1,
    "ratepayers": 1,
    "mid": 1,
    "february": 2,
    "seven": 1,
    "people": 1,
    "stood": 1,
    "since": 1,
    "number": 1,
    "vacancies": 1,
    "declared": 1,
    "26": 1,
    "levien": 1,
    "accepted": 1,
    "position": 1,
    "served": 1,
    "second": 1,
    "period": 1,
    "1877": 1,
    "retired": 2,
    "22": 1,
    "november": 1,
    "1881": 1,
    "described": 1,
    "happier": 1,
    "hosted": 1,
    "another": 1,
    "lord": 1,
    "rosmead": 1,
    "also": 1,
    "lobbied": 1,
    "extend": 1,
    "existing": 1,
    "railway": 1,
    "link": 1,
    "main": 1,
    "line": 1,
    "blenheim": 1,
    "edward": 1,
    "everett": 1,
    "place": 1,
    "died": 1,
    "aged": 1,
    "78": 1,
    "buried": 1,
    "wakapuaka": 1,
    "cemetery": 1,
    "14": 1,
    "references": 1
  },
  "title-length": 2,
  "content-length": 375,
  "curious_frequency": 0,
  "uplifting_frequency": 0,
  "entertaining_frequency": 0,
  "sad_frequency": 4,
  "general_frequency": 0
}