{
  "title": "Richard Brindley",
  "content-preview": "Richard Michael Brindley (born 5 May 1993) is an English professional footballer who plays as a right-back for National League club Eastleigh.\nBrindley progressed through the academy at Norwich City, but was released in 2012 after failing to break into the first-team. He joined Chelmsford City, wher",
  "url": "https://en.wikipedia.org/wiki/Richard_Brindley",
  "pageid": 38254127,
  "title-terms": {
    "richard": 1,
    "brindley": 1
  },
  "content-terms": {
    "richard": 2,
    "michael": 1,
    "brindley": 39,
    "born": 2,
    "5": 3,
    "may": 8,
    "1993": 1,
    "english": 1,
    "professional": 5,
    "footballer": 1,
    "plays": 1,
    "rightback": 3,
    "national": 3,
    "league": 16,
    "club": 13,
    "eastleigh": 3,
    "progressed": 1,
    "academy": 1,
    "norwich": 5,
    "city": 7,
    "released": 2,
    "2012": 3,
    "failing": 1,
    "break": 1,
    "firstteam": 5,
    "joined": 6,
    "chelmsford": 6,
    "performances": 1,
    "attracted": 1,
    "attention": 1,
    "chesterfield": 6,
    "signed": 12,
    "two": 5,
    "side": 9,
    "january": 8,
    "2013": 5,
    "would": 7,
    "make": 3,
    "debut": 10,
    "rotherham": 11,
    "united": 20,
    "struggled": 1,
    "hold": 1,
    "regular": 2,
    "starting": 8,
    "berth": 1,
    "one": 11,
    "goal": 8,
    "came": 4,
    "5\u20131": 2,
    "defeat": 3,
    "bournemouth": 2,
    "fa": 6,
    "cup": 4,
    "2015": 6,
    "subsequently": 1,
    "loaned": 1,
    "2014\u201315": 2,
    "season": 20,
    "scunthorpe": 5,
    "oxford": 5,
    "colchester": 10,
    "following": 10,
    "release": 3,
    "summer": 2,
    "permanent": 3,
    "basis": 1,
    "barnet": 6,
    "july": 4,
    "2017": 3,
    "left": 3,
    "end": 12,
    "relegation": 1,
    "career": 3,
    "began": 1,
    "played": 5,
    "either": 1,
    "central": 1,
    "midfielder": 1,
    "fullback": 1,
    "age": 1,
    "nine": 2,
    "announced": 2,
    "october": 1,
    "2008": 1,
    "offered": 3,
    "scholarship": 1,
    "begin": 1,
    "june": 2,
    "2009": 2,
    "broke": 2,
    "youth": 1,
    "team": 1,
    "scoring": 2,
    "aston": 1,
    "villa": 1,
    "coming": 3,
    "substitute": 4,
    "year": 1,
    "turning": 1,
    "new": 6,
    "contract": 6,
    "yet": 1,
    "appearance": 4,
    "conference": 2,
    "south": 2,
    "carrow": 1,
    "road": 1,
    "made": 12,
    "18": 1,
    "august": 3,
    "1\u20131": 2,
    "draw": 4,
    "havant": 1,
    "waterlooville": 1,
    "west": 1,
    "leigh": 1,
    "park": 2,
    "time": 3,
    "game": 6,
    "uk": 1,
    "football": 3,
    "finder": 1,
    "elite": 1,
    "development": 1,
    "squad": 2,
    "12": 2,
    "september": 3,
    "match": 5,
    "leatherhead": 1,
    "xi": 1,
    "4\u20132": 2,
    "victors": 1,
    "scored": 5,
    "first": 12,
    "10": 4,
    "december": 3,
    "defeated": 1,
    "hampton": 1,
    "richmond": 1,
    "borough": 1,
    "3\u20132": 1,
    "trophy": 3,
    "minute": 1,
    "play": 1,
    "final": 4,
    "3\u20130": 3,
    "halifax": 1,
    "town": 4,
    "shay": 1,
    "ten": 1,
    "appearances": 10,
    "three": 4,
    "addition": 1,
    "also": 3,
    "featured": 1,
    "four": 2,
    "times": 1,
    "including": 1,
    "round": 3,
    "3\u20131": 1,
    "win": 9,
    "second": 2,
    "crawley": 1,
    "24": 2,
    "competitions": 2,
    "awarded": 1,
    "man": 1,
    "awards": 1,
    "17": 2,
    "deal": 4,
    "running": 1,
    "2012\u201313": 1,
    "outing": 1,
    "derbyshire": 1,
    "senior": 1,
    "29": 2,
    "chesterfields": 1,
    "belper": 1,
    "coach": 1,
    "john": 2,
    "dungworth": 1,
    "pleased": 1,
    "brindleys": 1,
    "saying": 1,
    "energetic": 1,
    "full": 3,
    "confidence": 1,
    "prior": 1,
    "making": 5,
    "said": 5,
    "chance": 1,
    "showed": 1,
    "great": 2,
    "opportunity": 2,
    "progress": 1,
    "like": 1,
    "stay": 1,
    "longer": 1,
    "9": 1,
    "february": 1,
    "danny": 1,
    "whitaker": 1,
    "minutes": 5,
    "2\u20130": 3,
    "home": 4,
    "afc": 1,
    "wimbledon": 1,
    "though": 1,
    "limited": 1,
    "playing": 3,
    "grateful": 1,
    "provided": 2,
    "assist": 1,
    "marc": 1,
    "richards": 1,
    "score": 4,
    "1\u20130": 2,
    "16": 2,
    "march": 3,
    "spireites": 1,
    "dropped": 1,
    "ahead": 1,
    "april": 4,
    "contractual": 1,
    "issues": 1,
    "negotiations": 1,
    "parties": 1,
    "concerning": 1,
    "extension": 1,
    "eventually": 2,
    "twelve": 1,
    "games": 2,
    "longterm": 1,
    "future": 1,
    "still": 1,
    "resolved": 1,
    "campaign": 1,
    "expiry": 1,
    "23": 3,
    "twoyear": 3,
    "york": 1,
    "stadium": 2,
    "manager": 2,
    "steve": 1,
    "evans": 1,
    "watched": 1,
    "occasions": 1,
    "knew": 1,
    "top": 1,
    "talent": 1,
    "move": 2,
    "added": 1,
    "determined": 1,
    "prove": 1,
    "level": 1,
    "setting": 1,
    "target": 1,
    "getting": 1,
    "experience": 2,
    "opening": 1,
    "2013\u201314": 1,
    "3\u20133": 1,
    "crewe": 2,
    "alexandra": 1,
    "weeks": 1,
    "held": 2,
    "spot": 1,
    "injury": 2,
    "utility": 1,
    "player": 1,
    "mark": 1,
    "bradley": 1,
    "competition": 1,
    "position": 2,
    "across": 2,
    "onloan": 1,
    "newcastle": 1,
    "james": 1,
    "tavernier": 1,
    "fell": 1,
    "favour": 1,
    "early": 1,
    "part": 1,
    "2014": 4,
    "twice": 2,
    "host": 1,
    "injuries": 3,
    "saw": 3,
    "recalled": 1,
    "lineup": 1,
    "rotherhams": 2,
    "playoff": 2,
    "leg": 1,
    "preston": 1,
    "north": 1,
    "substituted": 1,
    "reached": 1,
    "started": 1,
    "bench": 1,
    "wes": 1,
    "thomas": 1,
    "54": 1,
    "wembley": 1,
    "leyton": 1,
    "orient": 1,
    "millers": 1,
    "pegged": 1,
    "back": 1,
    "2\u20132": 2,
    "secured": 1,
    "promotion": 2,
    "championship": 2,
    "4\u20133": 1,
    "penalty": 1,
    "shootout": 1,
    "despite": 1,
    "helping": 1,
    "89thminute": 1,
    "ben": 1,
    "pringle": 1,
    "millwall": 1,
    "den": 1,
    "3": 2,
    "loan": 9,
    "spell": 1,
    "third": 1,
    "encounter": 1,
    "lose": 1,
    "25": 4,
    "november": 1,
    "return": 1,
    "signing": 1,
    "13": 1,
    "scunthorpes": 1,
    "2\u20131": 3,
    "returned": 2,
    "due": 1,
    "month": 1,
    "view": 1,
    "31": 1,
    "beat": 1,
    "stevenage": 1,
    "brought": 1,
    "george": 1,
    "baldock": 1,
    "mk": 1,
    "dons": 1,
    "shortterm": 1,
    "expired": 1,
    "26": 1,
    "ipswich": 1,
    "loanee": 2,
    "elliott": 1,
    "hewitts": 1,
    "recall": 1,
    "revealed": 2,
    "turned": 1,
    "offers": 1,
    "order": 1,
    "join": 1,
    "could": 1,
    "later": 2,
    "become": 2,
    "colchesters": 6,
    "port": 1,
    "vale": 2,
    "eight": 1,
    "talks": 1,
    "former": 1,
    "2": 1,
    "8": 2,
    "blackpool": 1,
    "ever": 1,
    "2016": 1,
    "introduced": 1,
    "secondhalf": 1,
    "elliot": 1,
    "lee": 1,
    "doncaster": 1,
    "rovers": 1,
    "87thminute": 1,
    "shot": 1,
    "completed": 1,
    "4\u20131": 1,
    "victory": 2,
    "ended": 2,
    "mcgreal": 1,
    "became": 1,
    "eleven": 1,
    "2016\u201317": 1,
    "operated": 1,
    "right": 1,
    "wingback": 2,
    "352": 1,
    "formation": 1,
    "last": 1,
    "wasnt": 1,
    "managers": 1,
    "brilliant": 1,
    "feel": 1,
    "im": 1,
    "well": 1,
    "thats": 1,
    "want": 1,
    "best": 1,
    "free": 2,
    "kick": 1,
    "morecambe": 1,
    "43": 1,
    "opted": 1,
    "leave": 1,
    "refusing": 1,
    "terms": 1,
    "rivals": 1,
    "transfer": 1,
    "2018": 3,
    "relegated": 1,
    "mutual": 1,
    "consent": 1,
    "7": 1,
    "bromley": 2,
    "away": 1,
    "ebbsfleet": 1,
    "90": 1,
    "went": 1,
    "36": 1,
    "leaving": 1,
    "notts": 4,
    "county": 4,
    "2019": 1,
    "2022": 1,
    "28": 1,
    "2024": 2,
    "statistics": 1,
    "2023\u201324": 1,
    "honours": 1,
    "playoffs": 1,
    "2023": 1,
    "references": 1,
    "external": 1,
    "links": 1,
    "soccerbase": 1
  },
  "title-length": 2,
  "content-length": 996,
  "curious_frequency": 0,
  "uplifting_frequency": 2,
  "entertaining_frequency": 0,
  "sad_frequency": 0,
  "general_frequency": 0
}