{
  "title": "The End of Silence",
  "content-preview": "The End of Silence is the third studio album by the American rock band Rollins Band, led by former Black Flag singer Henry Rollins.  The album spawned two singles, including the MTV hit \"Low Self Opinion\". It was their first release to reach the US Billboard 200 chart, and is considered their mainst",
  "url": "https://en.wikipedia.org/wiki/The_End_of_Silence",
  "pageid": 4011188,
  "title-terms": {
    "end": 1,
    "silence": 1
  },
  "content-terms": {
    "end": 10,
    "silence": 10,
    "third": 1,
    "studio": 2,
    "album": 10,
    "american": 1,
    "rock": 7,
    "band": 12,
    "rollins": 19,
    "led": 2,
    "former": 2,
    "black": 4,
    "flag": 4,
    "singer": 2,
    "henry": 6,
    "spawned": 1,
    "two": 2,
    "singles": 2,
    "including": 1,
    "mtv": 1,
    "hit": 1,
    "low": 2,
    "self": 3,
    "opinion": 2,
    "first": 3,
    "release": 3,
    "reach": 1,
    "us": 1,
    "billboard": 2,
    "200": 1,
    "chart": 1,
    "considered": 3,
    "mainstream": 1,
    "breakthrough": 1,
    "previously": 1,
    "released": 5,
    "string": 1,
    "underground": 2,
    "albums": 8,
    "background": 1,
    "bands": 1,
    "independent": 1,
    "label": 6,
    "imago": 2,
    "records": 5,
    "signed": 1,
    "eight": 1,
    "contract": 1,
    "back": 2,
    "performance": 1,
    "inaugural": 1,
    "edition": 1,
    "lollapalooza": 2,
    "1991": 2,
    "time": 2,
    "distribution": 1,
    "deal": 1,
    "bmg": 1,
    "considering": 1,
    "major": 2,
    "debut": 1,
    "claimed": 1,
    "title": 1,
    "reference": 1,
    "broader": 1,
    "exposure": 1,
    "would": 2,
    "get": 3,
    "larger": 1,
    "1992": 11,
    "commented": 1,
    "weird": 2,
    "thing": 1,
    "walk": 1,
    "ive": 2,
    "made": 1,
    "dont": 2,
    "know": 1,
    "many": 2,
    "paid": 2,
    "maybe": 1,
    "three": 2,
    "times": 3,
    "life": 2,
    "royalty": 1,
    "check": 1,
    "mail": 1,
    "whats": 1,
    "say": 2,
    "make": 1,
    "thats": 1,
    "recorded": 2,
    "six": 2,
    "weeks": 1,
    "october": 2,
    "showplace": 1,
    "studios": 1,
    "dover": 1,
    "new": 1,
    "jersey": 1,
    "songs": 2,
    "already": 1,
    "written": 2,
    "previous": 1,
    "1989s": 1,
    "hard": 7,
    "volume": 2,
    "regarding": 2,
    "lyrical": 2,
    "content": 1,
    "said": 4,
    "wrote": 4,
    "lyrics": 1,
    "really": 3,
    "challenged": 1,
    "finally": 1,
    "courage": 1,
    "write": 2,
    "father": 1,
    "song": 1,
    "like": 2,
    "problems": 1,
    "dealing": 1,
    "past": 2,
    "cover": 1,
    "features": 1,
    "stylized": 1,
    "drawing": 1,
    "sun": 1,
    "identical": 1,
    "one": 3,
    "tattooed": 1,
    "liner": 1,
    "notes": 1,
    "credit": 1,
    "artwork": 1,
    "california": 1,
    "tattoo": 1,
    "artist": 1,
    "rick": 1,
    "spellman": 1,
    "musical": 1,
    "style": 1,
    "1999": 1,
    "book": 2,
    "vh1": 1,
    "stars": 2,
    "encyclopedia": 1,
    "authors": 1,
    "dafydd": 1,
    "rees": 1,
    "luke": 1,
    "crampton": 1,
    "described": 1,
    "mixing": 2,
    "elements": 1,
    "blues": 3,
    "jazz": 2,
    "otherwise": 1,
    "uncompromisingly": 1,
    "intense": 2,
    "punkmetal": 1,
    "set": 1,
    "metal": 6,
    "hammer": 2,
    "2021": 2,
    "sound": 6,
    "later": 1,
    "become": 1,
    "synonymous": 1,
    "saying": 1,
    "swing": 1,
    "prog": 1,
    "propped": 1,
    "altmetal": 1,
    "mixture": 1,
    "styles": 1,
    "guitarist": 1,
    "chris": 4,
    "haskett": 4,
    "2020": 1,
    "never": 2,
    "strategy": 1,
    "plan": 1,
    "writing": 3,
    "music": 3,
    "wouldn\u2019t": 1,
    "right": 1,
    "intended": 1,
    "combine": 1,
    "anything": 1,
    "particular": 1,
    "guitar": 2,
    "world": 1,
    "labelled": 2,
    "heaviest": 1,
    "point": 1,
    "also": 2,
    "noted": 2,
    "less": 1,
    "punkinfluenced": 1,
    "prior": 2,
    "works": 1,
    "edge": 1,
    "especially": 1,
    "van": 2,
    "halen": 1,
    "starts": 1,
    "creeping": 1,
    "colors": 1,
    "together": 1,
    "fully": 1,
    "took": 1,
    "ensemble": 1,
    "voice": 1,
    "collective": 1,
    "think": 1,
    "organic": 1,
    "earlier": 1,
    "reception": 2,
    "received": 2,
    "positive": 2,
    "reviews": 1,
    "critics": 1,
    "1996": 1,
    "sold": 1,
    "260000": 1,
    "copies": 1,
    "making": 2,
    "commercially": 1,
    "successful": 1,
    "1994s": 1,
    "weight": 2,
    "stephen": 1,
    "thomas": 1,
    "erlewine": 2,
    "allmusic": 1,
    "gave": 3,
    "four": 2,
    "five": 1,
    "review": 4,
    "observed": 1,
    "substantial": 1,
    "airplay": 1,
    "mtvs": 1,
    "headbangers": 1,
    "ball": 1,
    "program": 1,
    "cemented": 1,
    "profile": 1,
    "yet": 1,
    "another": 2,
    "audience": 1,
    "metalheads": 1,
    "solid": 1,
    "remains": 1,
    "best": 6,
    "reports": 1,
    "february": 2,
    "states": 1,
    "influence": 1,
    "bleeds": 1,
    "alternative": 2,
    "ranks": 1,
    "variety": 1,
    "forms": 1,
    "adding": 2,
    "blast": 1,
    "form": 1,
    "enjoy": 1,
    "warm": 1,
    "radio": 1,
    "perhaps": 1,
    "makes": 1,
    "leap": 1,
    "majors": 1,
    "without": 1,
    "compromising": 1,
    "earbending": 1,
    "creamed": 1,
    "unsuspecting": 1,
    "audiences": 1,
    "tour": 1,
    "last": 2,
    "year": 2,
    "jon": 1,
    "dominguez": 1,
    "californian": 1,
    "paper": 1,
    "palo": 1,
    "verde": 1,
    "valley": 1,
    "sounds": 1,
    "feels": 1,
    "real": 2,
    "tracks": 1,
    "ten": 2,
    "eleven": 1,
    "minutes": 3,
    "long": 1,
    "lose": 1,
    "interest": 1,
    "steve": 1,
    "hochman": 1,
    "los": 1,
    "angeles": 1,
    "half": 1,
    "rating": 1,
    "march": 2,
    "crowning": 1,
    "achievement": 1,
    "career": 1,
    "december": 1,
    "writer": 1,
    "morris": 1,
    "named": 1,
    "praising": 1,
    "pushing": 1,
    "outside": 1,
    "envelope": 1,
    "negative": 1,
    "came": 1,
    "pittsburgh": 1,
    "postgazettes": 1,
    "tony": 1,
    "norman": 1,
    "called": 1,
    "step": 1,
    "backwards": 1,
    "rocks": 1,
    "indulgent": 1,
    "since": 1,
    "lot": 1,
    "hipsters": 1,
    "seem": 1,
    "care": 1,
    "traded": 1,
    "punk": 1,
    "aesthetic": 1,
    "jams": 1,
    "extend": 1,
    "beyond": 1,
    "logical": 1,
    "conclusion": 1,
    "ill": 1,
    "state": 1,
    "obvious": 1,
    "anyone": 1,
    "wades": 1,
    "72": 1,
    "\u2014": 1,
    "boring": 1,
    "man": 1,
    "legacy": 1,
    "tool": 1,
    "bassist": 1,
    "justin": 1,
    "chancellor": 1,
    "mentioned": 1,
    "fan": 1,
    "2006": 1,
    "retrospective": 1,
    "albert": 1,
    "mudrian": 1,
    "decibel": 1,
    "magazine": 1,
    "kurt": 1,
    "cobain": 1,
    "altering": 1,
    "course": 1,
    "popular": 1,
    "music\u2019s": 1,
    "history": 1,
    "icon": 1,
    "busy": 1,
    "eating": 1,
    "cheese": 1,
    "sandwiches": 1,
    "avoiding": 1,
    "temptations": 1,
    "nearby": 1,
    "stripper": 1,
    "joints": 1,
    "putting": 1,
    "masterpiece": 1,
    "dark": 1,
    "angular": 1,
    "grooves": 1,
    "introspective": 1,
    "firestorms": 1,
    "tape": 1,
    "2009": 1,
    "spray": 1,
    "paint": 1,
    "walls": 1,
    "story": 1,
    "author": 1,
    "stevie": 1,
    "chick": 1,
    "themes": 1,
    "similar": 1,
    "muscular": 1,
    "ultimately": 1,
    "audiencepleasing": 1,
    "2022": 1,
    "louder": 1,
    "ranked": 1,
    "second": 1,
    "behind": 1,
    "spin": 1,
    "included": 2,
    "list": 2,
    "titled": 1,
    "30": 2,
    "overlooked": 1,
    "turning": 1,
    "20": 1,
    "listed": 1,
    "100": 1,
    "1990s": 1,
    "accolades": 1,
    "track": 1,
    "listing": 1,
    "andrew": 2,
    "weiss": 2,
    "sim": 2,
    "cain": 2,
    "\u2013": 17,
    "518": 1,
    "grip": 1,
    "450": 1,
    "tearing": 1,
    "458": 1,
    "didnt": 1,
    "need": 1,
    "530": 1,
    "almost": 1,
    "803": 1,
    "obscene": 1,
    "850": 1,
    "722": 1,
    "jam": 1,
    "1146": 1,
    "439": 1,
    "1057": 1,
    "personnel": 1,
    "vocals": 1,
    "bass": 1,
    "drums": 1,
    "production": 2,
    "theo": 1,
    "engineering": 2,
    "andy": 1,
    "wallace": 1,
    "howie": 1,
    "weinberg": 1,
    "mastering": 1,
    "charts": 1,
    "references": 1
  },
  "title-length": 2,
  "content-length": 715,
  "curious_frequency": 2,
  "uplifting_frequency": 4,
  "entertaining_frequency": 1,
  "sad_frequency": 0,
  "general_frequency": 0
}