{
  "title": "The Windsors",
  "content-preview": "The Windsors is a British sitcom and parody of the British royal family, the House of Windsor. It was first broadcast on Channel 4 in April 2016 and stars Harry Enfield, Haydn Gwynne, Hugh Skinner, Louise Ford, Richard Goulding, Tom Durant-Pritchard, Kathryn Drysdale, Morgana Robinson, Ellie White, ",
  "url": "https://en.wikipedia.org/wiki/The_Windsors",
  "pageid": 50453526,
  "title-terms": {
    "windsors": 1
  },
  "content-terms": {
    "windsors": 11,
    "british": 4,
    "sitcom": 2,
    "parody": 3,
    "royal": 11,
    "family": 6,
    "house": 2,
    "windsor": 1,
    "first": 3,
    "broadcast": 2,
    "channel": 2,
    "4": 2,
    "april": 2,
    "2016": 3,
    "stars": 1,
    "harry": 10,
    "enfield": 4,
    "haydn": 3,
    "gwynne": 3,
    "hugh": 2,
    "skinner": 2,
    "louise": 2,
    "ford": 2,
    "richard": 2,
    "goulding": 2,
    "tom": 3,
    "durantpritchard": 3,
    "kathryn": 2,
    "drysdale": 2,
    "morgana": 2,
    "robinson": 2,
    "ellie": 3,
    "white": 3,
    "celeste": 3,
    "dring": 3,
    "written": 2,
    "cocreators": 1,
    "star": 1,
    "stories": 3,
    "bert": 2,
    "tylermoore": 4,
    "george": 2,
    "jeffrie": 4,
    "satirical": 1,
    "portrayal": 1,
    "following": 3,
    "death": 2,
    "heart": 1,
    "attack": 1,
    "september": 1,
    "2020": 2,
    "became": 1,
    "sole": 1,
    "writer": 1,
    "series": 22,
    "fourth": 5,
    "scheduled": 1,
    "film": 1,
    "late": 2,
    "2023": 5,
    "coronation": 6,
    "special": 9,
    "episode": 2,
    "earlier": 1,
    "year": 1,
    "production": 2,
    "suspended": 1,
    "early": 2,
    "2024": 3,
    "synopsis": 1,
    "tells": 1,
    "story": 1,
    "reimagined": 2,
    "soap": 3,
    "opera": 3,
    "although": 2,
    "completely": 3,
    "fictional": 2,
    "inspired": 2,
    "real": 2,
    "events": 3,
    "cast": 3,
    "main": 1,
    "prince": 6,
    "later": 3,
    "king": 3,
    "charles": 12,
    "oldest": 1,
    "son": 2,
    "heir": 2,
    "apparent": 2,
    "elizabeth": 1,
    "ii": 1,
    "spends": 1,
    "three": 1,
    "impatiently": 1,
    "waiting": 1,
    "mother": 2,
    "die": 1,
    "finally": 1,
    "united": 1,
    "kingdom": 1,
    "portrayed": 4,
    "selfabsorbed": 1,
    "naive": 2,
    "overconfident": 1,
    "abilities": 1,
    "prone": 1,
    "believe": 1,
    "comically": 1,
    "absurd": 1,
    "theories": 1,
    "little": 3,
    "knowledge": 1,
    "world": 1,
    "outside": 2,
    "monarchy": 3,
    "also": 5,
    "enjoys": 1,
    "inventing": 1,
    "whimsical": 1,
    "ideas": 1,
    "feels": 1,
    "underappreciated": 1,
    "running": 1,
    "gag": 1,
    "fondness": 1,
    "wearing": 1,
    "kilts": 1,
    "without": 1,
    "undergarments": 1,
    "ascends": 1,
    "throne": 1,
    "portrays": 1,
    "twominutesolder": 1,
    "identical": 1,
    "twin": 1,
    "brother": 5,
    "chuck": 1,
    "2": 4,
    "3": 3,
    "princess": 6,
    "queen": 2,
    "camilla": 5,
    "second": 2,
    "wife": 5,
    "depicted": 5,
    "stereotypical": 1,
    "conniving": 1,
    "villain": 2,
    "determined": 1,
    "become": 2,
    "replace": 1,
    "lineage": 1,
    "redeeming": 1,
    "eyes": 1,
    "public": 1,
    "result": 2,
    "usurping": 1,
    "dianas": 1,
    "position": 1,
    "fixates": 1,
    "various": 1,
    "ways": 1,
    "might": 3,
    "achieve": 1,
    "never": 1,
    "fulfills": 1,
    "schemes": 1,
    "imagines": 1,
    "william": 2,
    "wills": 7,
    "wellmeaning": 1,
    "royals": 3,
    "whose": 1,
    "manner": 1,
    "speech": 1,
    "exaggerates": 1,
    "parts": 2,
    "received": 1,
    "pronunciation": 1,
    "often": 2,
    "attempts": 1,
    "leave": 1,
    "get": 1,
    "abolished": 1,
    "simply": 1,
    "grow": 1,
    "familys": 2,
    "shadow": 1,
    "pursuing": 1,
    "interests": 1,
    "career": 1,
    "opportunities": 1,
    "duties": 1,
    "receives": 1,
    "advice": 1,
    "counsel": 1,
    "spirits": 1,
    "previous": 1,
    "monarchs": 1,
    "england": 1,
    "whole": 2,
    "uk": 1,
    "catherine": 1,
    "kate": 2,
    "n\u00e9e": 1,
    "middleton": 2,
    "former": 2,
    "gypsy": 1,
    "wants": 1,
    "better": 1,
    "fit": 1,
    "1\u20132": 1,
    "immature": 1,
    "younger": 4,
    "taken": 1,
    "advantage": 1,
    "women": 1,
    "illiterate": 1,
    "end": 3,
    "1": 4,
    "meghan": 3,
    "markle": 1,
    "2\u20133": 1,
    "harrys": 2,
    "girlfriend": 1,
    "shallow": 2,
    "narcissist": 1,
    "still": 1,
    "obsessed": 1,
    "time": 1,
    "acting": 1,
    "american": 1,
    "legal": 1,
    "drama": 2,
    "tv": 2,
    "suits": 1,
    "presenting": 1,
    "strong": 1,
    "independent": 1,
    "woman": 1,
    "despite": 2,
    "desire": 1,
    "marry": 1,
    "pippa": 3,
    "kates": 1,
    "sister": 2,
    "passiveaggressive": 1,
    "greedy": 1,
    "promiscuous": 1,
    "envious": 1,
    "social": 1,
    "climber": 1,
    "pursues": 1,
    "relationship": 1,
    "continues": 1,
    "trying": 1,
    "win": 1,
    "back": 2,
    "begins": 1,
    "dating": 1,
    "beatrice": 6,
    "eugenie": 5,
    "cousins": 1,
    "two": 2,
    "useless": 2,
    "rich": 1,
    "sloanes": 1,
    "searching": 1,
    "purpose": 1,
    "life": 2,
    "recurring": 1,
    "matthew": 2,
    "cottle": 2,
    "edward": 3,
    "youngest": 1,
    "fails": 1,
    "many": 1,
    "things": 1,
    "katy": 2,
    "wix": 2,
    "sarah": 1,
    "fergie": 2,
    "ferguson": 1,
    "eugenies": 1,
    "desperate": 1,
    "let": 2,
    "inner": 1,
    "circle": 1,
    "tim": 2,
    "wallers": 2,
    "andrew": 2,
    "fergies": 1,
    "husband": 1,
    "sleazy": 1,
    "manipulative": 1,
    "businessman": 1,
    "vicki": 1,
    "pepperdine": 1,
    "anne": 1,
    "austere": 1,
    "menacing": 1,
    "almost": 1,
    "ghostlike": 1,
    "sudden": 1,
    "appearances": 1,
    "preceded": 1,
    "drop": 1,
    "temperature": 1,
    "freezes": 1,
    "peoples": 1,
    "breath": 1,
    "passion": 1,
    "horses": 1,
    "gordon": 1,
    "kennedy": 1,
    "alec": 1,
    "tony": 1,
    "jayawardena": 1,
    "sandy": 1,
    "scottish": 1,
    "bystanders": 1,
    "comment": 2,
    "donovan": 1,
    "blackwood": 1,
    "baxter": 1,
    "military": 1,
    "recruiter": 1,
    "drill": 1,
    "instructor": 1,
    "trains": 1,
    "air": 1,
    "ambulance": 1,
    "pilot": 1,
    "anna": 1,
    "morris": 1,
    "sophie": 1,
    "edwards": 1,
    "guests": 1,
    "historical": 1,
    "figures": 1,
    "episodes": 1,
    "overview": 1,
    "christmas": 1,
    "2017": 1,
    "wedding": 2,
    "2018": 1,
    "prospective": 1,
    "unofficially": 1,
    "confirmed": 1,
    "spring": 1,
    "prior": 1,
    "plots": 1,
    "revealed": 1,
    "include": 1,
    "prolonging": 1,
    "halfhour": 1,
    "weekly": 1,
    "meeting": 1,
    "prime": 1,
    "minister": 1,
    "allafternoon": 1,
    "brainstorming": 1,
    "session": 1,
    "demanding": 1,
    "place": 2,
    "cabinet": 1,
    "ending": 1,
    "bromance": 1,
    "welsh": 1,
    "nationalist": 1,
    "rescuing": 1,
    "new": 1,
    "zealand": 1,
    "brink": 1,
    "leaving": 1,
    "commonwealth": 1,
    "timetravelling": 1,
    "accidentally": 1,
    "altering": 1,
    "order": 1,
    "succession": 1,
    "filming": 1,
    "stated": 1,
    "taking": 1,
    "died": 1,
    "october": 2,
    "announced": 2,
    "indefinitely": 1,
    "postponed": 1,
    "owing": 1,
    "reallife": 1,
    "health": 1,
    "scares": 1,
    "affecting": 1,
    "senior": 1,
    "members": 2,
    "reported": 1,
    "plans": 1,
    "arranged": 1,
    "recast": 1,
    "role": 1,
    "gwynnes": 1,
    "write": 1,
    "characters": 2,
    "concentrate": 1,
    "generations": 1,
    "majesties": 1,
    "away": 1,
    "tour": 1,
    "reception": 1,
    "guardian": 3,
    "favourable": 1,
    "said": 2,
    "highbrow": 1,
    "humour": 1,
    "number": 1,
    "crew": 1,
    "comparing": 1,
    "show": 4,
    "spitting": 1,
    "image": 1,
    "doesnt": 2,
    "feel": 1,
    "like": 3,
    "satire": 1,
    "comic": 1,
    "makes": 1,
    "odd": 1,
    "described": 2,
    "statement": 1,
    "wry": 1,
    "take": 2,
    "lives": 1,
    "loves": 1,
    "delving": 1,
    "behind": 1,
    "headlines": 1,
    "gossip": 1,
    "columns": 1,
    "lets": 1,
    "imaginations": 1,
    "run": 1,
    "riot": 1,
    "ludicrous": 2,
    "imagine": 1,
    "really": 3,
    "controls": 1,
    "sceptre": 1,
    "camillas": 1,
    "marriage": 1,
    "think": 1,
    "want": 1,
    "ever": 2,
    "aisle": 1,
    "bum": 1,
    "note": 1,
    "actually": 1,
    "living": 1,
    "c4s": 1,
    "head": 1,
    "comedy": 3,
    "phil": 1,
    "clarke": 1,
    "added": 1,
    "muchloved": 1,
    "lens": 1,
    "writers": 1,
    "outdone": 1,
    "even": 1,
    "funniest": 1,
    "issue": 1,
    "hello": 1,
    "magazine": 1,
    "daily": 1,
    "telegraph": 2,
    "wrote": 2,
    "lowbudget": 1,
    "crude": 1,
    "rude": 1,
    "done": 1,
    "cacophonous": 1,
    "relish": 1,
    "resistance": 1,
    "theres": 1,
    "much": 1,
    "kind": 1,
    "punk": 1,
    "around": 1,
    "television": 1,
    "moment": 1,
    "deep": 1,
    "mordant": 1,
    "officestyle": 1,
    "irony": 1,
    "long": 1,
    "dominant": 1,
    "mode": 1,
    "mischief": 1,
    "fan": 1,
    "beethoven": 1,
    "buzzcocks": 1,
    "review": 1,
    "list": 1,
    "brian": 1,
    "donaldson": 1,
    "pitiful": 1,
    "buck": 1,
    "way": 2,
    "writing": 2,
    "would": 3,
    "coming": 1,
    "bit": 2,
    "thick": 1,
    "rather": 1,
    "attentionseeking": 1,
    "cartoon": 1,
    "course": 1,
    "wouldnt": 1,
    "obvious": 2,
    "though": 1,
    "maybe": 1,
    "could": 1,
    "go": 1,
    "road": 1,
    "put": 1,
    "spin": 1,
    "somehow": 1,
    "lot": 1,
    "less": 1,
    "making": 1,
    "lost": 1,
    "soul": 1,
    "empty": 1,
    "diary": 1,
    "squarejawed": 1,
    "helicopter": 1,
    "hero": 1,
    "enjoying": 1,
    "people": 1,
    "constantly": 1,
    "gazing": 1,
    "fantastic": 1,
    "arse": 1,
    "incredibly": 1,
    "duke": 1,
    "edinburgh": 1,
    "wait": 1,
    "racist": 1,
    "certainly": 1,
    "gratifying": 1,
    "see": 1,
    "upcoming": 1,
    "fringe": 1,
    "acts": 1,
    "landing": 1,
    "alltoo": 1,
    "predictably": 1,
    "blast": 1,
    "tragically": 1,
    "pitiable": 1,
    "mum": 1,
    "sadly": 1,
    "talent": 1,
    "woefully": 1,
    "predictable": 1,
    "utterly": 1,
    "laughfree": 1,
    "script": 1,
    "heads": 1,
    "season": 1,
    "riotous": 1,
    "hilarity": 1,
    "called": 2,
    "right": 1,
    "romp": 1,
    "sam": 1,
    "wollaston": 1,
    "worried": 1,
    "hour": 1,
    "stretch": 1,
    "neednt": 1,
    "suggested": 1,
    "spinoff": 1,
    "endgame": 2,
    "stage": 2,
    "play": 2,
    "9": 2,
    "june": 1,
    "2021": 2,
    "open": 1,
    "wales": 1,
    "theatre": 1,
    "londons": 1,
    "west": 1,
    "august": 1,
    "directed": 1,
    "michael": 1,
    "fentiman": 1,
    "featured": 1,
    "including": 1,
    "references": 1,
    "external": 1,
    "links": 1,
    "official": 1,
    "site": 1,
    "imdb": 1,
    "epguidescom": 1,
    "comedyuk": 1
  },
  "title-length": 1,
  "content-length": 932,
  "curious_frequency": 2,
  "uplifting_frequency": 3,
  "entertaining_frequency": 11,
  "sad_frequency": 3,
  "general_frequency": 0
}