{
  "title": "A Leg to Stand On",
  "content-preview": "A Leg to Stand On is a 1984 autobiographical account by neurologist Oliver Sacks describing his recovery from psychogenic leg paralysis following a mountaineering accident.  The book has been described as a skillful description of the depersonalization of functional neurological symptoms. Neuropsych",
  "url": "https://en.wikipedia.org/wiki/A_Leg_to_Stand_On",
  "pageid": 59182156,
  "title-terms": {
    "leg": 1,
    "stand": 1
  },
  "content-terms": {
    "leg": 15,
    "stand": 4,
    "1984": 1,
    "autobiographical": 2,
    "account": 2,
    "neurologist": 1,
    "oliver": 6,
    "sacks": 44,
    "describing": 1,
    "recovery": 3,
    "psychogenic": 1,
    "paralysis": 2,
    "following": 3,
    "mountaineering": 1,
    "accident": 2,
    "book": 4,
    "described": 3,
    "skillful": 1,
    "description": 1,
    "depersonalization": 2,
    "functional": 2,
    "neurological": 3,
    "symptoms": 2,
    "neuropsychiatric": 1,
    "specialists": 1,
    "recommended": 1,
    "reading": 1,
    "patients": 2,
    "found": 5,
    "help": 1,
    "cope": 1,
    "synopsis": 1,
    "early": 1,
    "saturday": 1,
    "morning": 3,
    "geared": 1,
    "climb": 1,
    "mountain": 3,
    "hardangerfjord": 1,
    "norway": 1,
    "despite": 5,
    "overcast": 1,
    "sullen": 1,
    "weather": 1,
    "reached": 1,
    "summit": 1,
    "noon": 1,
    "however": 3,
    "alone": 1,
    "bull": 1,
    "stood": 2,
    "feet": 1,
    "front": 1,
    "futile": 2,
    "attempt": 1,
    "remain": 1,
    "calm": 1,
    "lost": 2,
    "composure": 1,
    "tumbled": 1,
    "side": 2,
    "landing": 1,
    "atop": 1,
    "twisted": 1,
    "left": 3,
    "examining": 1,
    "injury": 1,
    "determined": 3,
    "entire": 1,
    "quadriceps": 3,
    "torn": 2,
    "patella": 1,
    "leaving": 1,
    "useless": 1,
    "made": 1,
    "makeshift": 1,
    "splint": 1,
    "immobilize": 1,
    "injured": 1,
    "order": 1,
    "slowly": 1,
    "slide": 1,
    "though": 1,
    "hope": 2,
    "sun": 1,
    "began": 5,
    "setting": 1,
    "fortunately": 1,
    "couple": 1,
    "reindeer": 1,
    "hunters": 1,
    "lying": 1,
    "path": 1,
    "last": 1,
    "bits": 1,
    "light": 1,
    "able": 1,
    "transport": 1,
    "local": 2,
    "hospital": 4,
    "treatment": 1,
    "upon": 4,
    "arriving": 2,
    "diagnosed": 1,
    "transferred": 1,
    "another": 1,
    "bergen": 1,
    "operation": 4,
    "done": 1,
    "reattach": 1,
    "muscle": 1,
    "according": 1,
    "surgeon": 1,
    "mr": 6,
    "swan": 1,
    "surgery": 1,
    "success": 2,
    "convinced": 1,
    "become": 1,
    "quite": 1,
    "obvious": 1,
    "healing": 1,
    "properly": 1,
    "arrival": 1,
    "physiotherapist": 2,
    "inability": 1,
    "contract": 1,
    "matter": 1,
    "hard": 1,
    "tried": 1,
    "woken": 1,
    "hanging": 1,
    "bed": 1,
    "feeling": 2,
    "nauseating": 1,
    "estrangement": 2,
    "towards": 3,
    "limb": 3,
    "foreign": 1,
    "inconceivable": 1,
    "thing": 1,
    "experienced": 1,
    "something": 2,
    "similar": 1,
    "patient": 3,
    "past": 1,
    "must": 1,
    "acquired": 1,
    "form": 1,
    "anosognosia": 1,
    "result": 2,
    "unfortunately": 1,
    "physicians": 1,
    "treating": 1,
    "acknowledge": 1,
    "illness": 1,
    "basis": 1,
    "anything": 1,
    "experiencing": 1,
    "simply": 1,
    "hysteria": 1,
    "two": 1,
    "weeks": 1,
    "begins": 1,
    "experience": 2,
    "involuntary": 1,
    "electrical": 1,
    "pulses": 1,
    "attributed": 1,
    "improvement": 1,
    "nothing": 1,
    "improve": 1,
    "mental": 1,
    "state": 1,
    "although": 1,
    "friend": 2,
    "brought": 2,
    "recorder": 1,
    "cassette": 1,
    "mendelssohns": 1,
    "violin": 1,
    "concerto": 1,
    "music": 4,
    "back": 1,
    "along": 2,
    "love": 1,
    "appreciation": 1,
    "life": 2,
    "next": 2,
    "day": 1,
    "cast": 2,
    "removed": 1,
    "could": 1,
    "shake": 1,
    "felt": 2,
    "naked": 1,
    "seemingly": 1,
    "session": 1,
    "notion": 2,
    "play": 1,
    "attempting": 1,
    "perform": 1,
    "exercise": 1,
    "meditated": 1,
    "without": 3,
    "thought": 2,
    "legs": 1,
    "miraculously": 1,
    "walk": 2,
    "weakness": 1,
    "epiphany": 1,
    "eventful": 1,
    "crucial": 1,
    "ten": 1,
    "minutes": 1,
    "recover": 1,
    "moved": 1,
    "convalescent": 1,
    "home": 2,
    "highgate": 1,
    "london": 1,
    "england": 1,
    "referred": 1,
    "time": 1,
    "caen": 1,
    "wood": 1,
    "met": 2,
    "group": 2,
    "fellow": 1,
    "veterans": 1,
    "offered": 1,
    "solace": 1,
    "sharing": 1,
    "stories": 1,
    "war": 1,
    "deal": 1,
    "phantom": 1,
    "syndrome": 1,
    "ironic": 1,
    "opposite": 1,
    "ordeal": 1,
    "men": 1,
    "wise": 1,
    "understanding": 1,
    "doctor": 1,
    "treated": 1,
    "permanent": 1,
    "removal": 1,
    "remained": 1,
    "numb": 1,
    "touch": 1,
    "progress": 1,
    "lack": 1,
    "sensitivity": 1,
    "due": 1,
    "severance": 1,
    "femoral": 1,
    "nerve": 4,
    "occurred": 1,
    "thereby": 1,
    "inhibiting": 1,
    "activity": 2,
    "causing": 1,
    "feel": 1,
    "disconnected": 1,
    "four": 1,
    "years": 1,
    "later": 1,
    "put": 1,
    "conduction": 1,
    "tests": 1,
    "better": 1,
    "understand": 1,
    "severity": 1,
    "damage": 1,
    "graduated": 1,
    "convalescence": 1,
    "office": 1,
    "wr": 3,
    "harley": 1,
    "street": 1,
    "asked": 1,
    "enjoyed": 1,
    "incident": 1,
    "responded": 1,
    "swimming": 1,
    "called": 1,
    "lifeguard": 3,
    "sent": 1,
    "way": 1,
    "pool": 3,
    "pushed": 1,
    "wrs": 2,
    "directions": 1,
    "protests": 1,
    "outraged": 1,
    "challenged": 1,
    "swim": 1,
    "regard": 1,
    "disability": 1,
    "told": 1,
    "finished": 1,
    "got": 1,
    "around": 1,
    "normally": 1,
    "still": 1,
    "limp": 1,
    "astonished": 1,
    "simple": 1,
    "effective": 1,
    "solution": 1,
    "incapable": 1,
    "physical": 1,
    "condelectari": 1,
    "sibi": 1,
    "received": 1,
    "letter": 1,
    "professor": 1,
    "luria": 1,
    "outlining": 1,
    "possible": 2,
    "reasons": 1,
    "alienation": 1,
    "treatments": 1,
    "point": 1,
    "clarity": 1,
    "support": 1,
    "allowing": 1,
    "finally": 1,
    "heal": 1,
    "reception": 1,
    "vic": 1,
    "sussman": 1,
    "washington": 1,
    "post": 1,
    "world": 1,
    "wrote": 2,
    "calling": 1,
    "neurology": 2,
    "soul": 1,
    "deeper": 1,
    "humane": 2,
    "medicine": 1,
    "remarkable": 1,
    "raises": 1,
    "issues": 1,
    "profound": 1,
    "importance": 1,
    "everyone": 1,
    "interested": 1,
    "health": 1,
    "care": 1,
    "human": 1,
    "application": 1,
    "science": 1,
    "ronald": 1,
    "carson": 1,
    "johns": 1,
    "hopkins": 1,
    "university": 1,
    "press": 1,
    "marvelous": 1,
    "mixture": 1,
    "observation": 1,
    "psychological": 1,
    "insight": 1,
    "mystical": 1,
    "speculative": 1,
    "vision": 1,
    "jon": 1,
    "stone": 1,
    "western": 1,
    "general": 1,
    "edinburgh": 1,
    "writing": 1,
    "journal": 1,
    "neurosurgery": 1,
    "psychiatry": 1,
    "defined": 1,
    "unique": 1,
    "references": 1,
    "external": 1,
    "links": 1,
    "internet": 1,
    "archive": 1,
    "even": 1,
    "youtube": 1,
    "channel": 1
  },
  "title-length": 2,
  "content-length": 564,
  "curious_frequency": 1,
  "uplifting_frequency": 5,
  "entertaining_frequency": 1,
  "sad_frequency": 3,
  "general_frequency": 0
}